MANIFEST.in
README.txt
setup.cfg
setup.py
docs/HISTORY.txt
docs/INSTALL.txt
docs/LICENSE.GPL
docs/LICENSE.txt
plonetheme/__init__.py
plonetheme.overlappedtabs.egg-info/PKG-INFO
plonetheme.overlappedtabs.egg-info/SOURCES.txt
plonetheme.overlappedtabs.egg-info/dependency_links.txt
plonetheme.overlappedtabs.egg-info/entry_points.txt
plonetheme.overlappedtabs.egg-info/namespace_packages.txt
plonetheme.overlappedtabs.egg-info/not-zip-safe
plonetheme.overlappedtabs.egg-info/paster_plugins.txt
plonetheme.overlappedtabs.egg-info/requires.txt
plonetheme.overlappedtabs.egg-info/top_level.txt
plonetheme/overlappedtabs/__init__.py
plonetheme/overlappedtabs/configure.zcml
plonetheme/overlappedtabs/profiles.zcml
plonetheme/overlappedtabs/setuphandlers.py
plonetheme/overlappedtabs/skins.zcml
plonetheme/overlappedtabs/tests.py
plonetheme/overlappedtabs/version.txt
plonetheme/overlappedtabs/Extensions/Install.py
plonetheme/overlappedtabs/Extensions/__init__.py
plonetheme/overlappedtabs/browser/__init__.py
plonetheme/overlappedtabs/browser/configure.zcml
plonetheme/overlappedtabs/browser/interfaces.py
plonetheme/overlappedtabs/browser/viewlets.py
plonetheme/overlappedtabs/browser/images/README.txt
plonetheme/overlappedtabs/browser/images/button_arrow.jpg
plonetheme/overlappedtabs/browser/images/disclaimer.png
plonetheme/overlappedtabs/browser/images/rounded_bl.png
plonetheme/overlappedtabs/browser/images/rounded_br.png
plonetheme/overlappedtabs/browser/images/rounded_tl.png
plonetheme/overlappedtabs/browser/images/rounded_tr.png
plonetheme/overlappedtabs/browser/images/section_images.png
plonetheme/overlappedtabs/browser/images/sections_line.png
plonetheme/overlappedtabs/browser/images/tabs_background.png
plonetheme/overlappedtabs/browser/portlets/__init__.py
plonetheme/overlappedtabs/browser/portlets/navigation.pt
plonetheme/overlappedtabs/browser/portlets/navigation.py
plonetheme/overlappedtabs/browser/portlets/navigation_recurse.pt
plonetheme/overlappedtabs/browser/stylesheets/README.txt
plonetheme/overlappedtabs/browser/stylesheets/main.css
plonetheme/overlappedtabs/browser/stylesheets/screen.css
plonetheme/overlappedtabs/browser/templates/colophon.pt
plonetheme/overlappedtabs/browser/templates/sections.pt
plonetheme/overlappedtabs/browser/templates/sections_line.pt
plonetheme/overlappedtabs/profiles/default/cssregistry.xml
plonetheme/overlappedtabs/profiles/default/import_steps.xml
