Metadata-Version: 1.0
Name: plonetheme.overlappedtabs
Version: 1.0dev-r111159
Summary: A theme for plone 3.x with overlapping tabs
Home-page: http://plone.org/products/plonetheme.overlappedtabs
Author: Javier Mansilla
Author-email: jmansilla@machinalis.com
License: GPL
Keywords: web zope plone theme overlapped tabs
Platform: UNKNOWN
Classifier: Framework :: Plone
Classifier: Programming Language :: Python
Classifier: Topic :: Software Development :: Libraries :: Python Modules
